setup.py
pywebqq/__init__.py
pywebqq/chatloggin.conf
pywebqq/client.py
pywebqq/qqsetting.py
pywebqq/requirement.txt
pywebqq/webqq.py
pywebqq.egg-info/PKG-INFO
pywebqq.egg-info/SOURCES.txt
pywebqq.egg-info/dependency_links.txt
pywebqq.egg-info/entry_points.txt
pywebqq.egg-info/requires.txt
pywebqq.egg-info/top_level.txt