Metadata-Version: 1.1
Name: pywebqq
Version: 0.2
Summary: 通过模拟WEBQQ3.0实现的命令行QQ聊天工具
Home-page: http://github.com/ftfniqpl/webqq-console
Author: alex8224@gmail.com, birdaccp@gmail.com
Author-email: alex8224@gmail.com, birdaccp@gmail.com
License: MIT License
Keywords: pyqq,pywebqq,webqq,pyweb
Platform: any
Classifier: License :: OSI Approved :: MIT License
Classifier: Programming Language :: Python :: 2
Classifier: Programming Language :: Python :: 2.6
Classifier: Programming Language :: Python :: 2.7
Classifier: Topic :: Utilities
